fluent_bundle/__init__.py
fluent_bundle/bundle.py
fluent_bundle-2.0.dist-info/DESCRIPTION.rst
fluent_bundle-2.0.dist-info/METADATA
fluent_bundle-2.0.dist-info/RECORD
fluent_bundle-2.0.dist-info/WHEEL
fluent_bundle-2.0.dist-info/metadata.json
fluent_bundle-2.0.dist-info/top_level.txt
