Metadata-Version: 2.0
Name: fluent-bundle
Version: 2.0
Summary: fluentd support for applauncher
Home-page: https://github.com/applauncher-team/fluent_bundle
Author: Alvaro Garcia Gomez
Author-email: maxpowel@gmail.com
License: UNKNOWN
Download-URL: https://github.com/applauncher-team/fluent_bundle
Keywords: fluentd,fluent,applauncher
Platform: UNKNOWN
Classifier: Topic :: Adaptive Technologies
Classifier: Topic :: Software Development
Classifier: Topic :: System
Classifier: Topic :: Utilities
Requires-Dist: applauncher
Requires-Dist: fluent-logger
